{"Id":"Problems/leetcode-83","Type":0,"Author":"","Content":{"Tag":"","Raw":"\n\u626B\u63CF\u4E00\u904D\u5373\u53EF\u3002\n\n\u0060\u0060\u0060rust\nimpl Solution {\n    pub fn delete_duplicates(head: Option\u003CBox\u003CListNode\u003E\u003E) -\u003E Option\u003CBox\u003CListNode\u003E\u003E {\n        let mut vals = Vec::new();\n        let mut cur = head;\n        while let Some(item) = cur {\n            vals.push(item.val);\n            cur = item.next;\n        }\n        vals.dedup();\n        let mut cur = None;\n        for val in vals.into_iter().rev() {\n            cur = Some(Box::new(ListNode { val, next: cur }));\n        }\n        cur\n    }\n}\n\u0060\u0060\u0060"},"Title":"LeetCode-83 \u5220\u9664\u6392\u5E8F\u94FE\u8868\u4E2D\u7684\u91CD\u590D\u5143\u7D20","Category":{"Items":["Problems"]},"Keywords":{"Items":["leetcode"]},"CreationTime":"2020-07-28T16:53:12+08:00","ModificationTime":"2020-07-28T16:53:12+08:00"}